flora_translator/__init__.py
flora_translator/translate_controls_content.py
flora_translator/translate_page.py
flora_translator/translate_support_language.py
flora_translator/translate_using_google.py
flora_translator/translate_using_mymemory.py
flora_translator-4.0.0.dist-info/LICENSE
flora_translator-4.0.0.dist-info/METADATA
flora_translator-4.0.0.dist-info/WHEEL
flora_translator-4.0.0.dist-info/top_level.txt
flora_translator-4.0.0.dist-info/RECORD
