Metadata-Version: 2.2
Name: flora_translator
Version: 4.0.0
Summary: A package that help flet developers to make their apps support multiple languages
Home-page: https://floraplant.ir
Author: Flora
Author-email: floraplantprocessing@gmail.com
Classifier: Programming Language :: Python :: 3
Classifier: Operating System :: MacOS :: MacOS X
Classifier: Operating System :: Microsoft :: Windows
License-File: LICENSE
Requires-Dist: flet
Dynamic: author
Dynamic: author-email
Dynamic: classifier
Dynamic: description
Dynamic: description-content-type
Dynamic: home-page
Dynamic: requires-dist
Dynamic: summary
